{
  "version": "2.0",
  "clipId": "1681612833",
  "format": "md",
  "title": "python+playwright 学习-27 鼠标悬停 hover() 和listitem 定位",
  "link": "https://www.cnblogs.com/yoyoketang/p/17198000.html",
  "category": "Coding",
  "tags": [
    "playwright",
    "python"
  ],
  "created_at": "2023-04-16 10:40:33",
  "mainPath": "index.md",
  "paths": [
    "index.json",
    "a-title_python-playwright-学习-27-鼠标悬停-hover-和listitem-定位",
    "assets/1681612833-83887ca6de7478d84c4319e24d8901ff.png",
    "assets/1681612833-f26f33a88b409628f2b665a0da1518f9.png",
    "assets/1681612833-570a9ce3948fa801e767328fac6d402b.png",
    "index.md"
  ]
}